{
	"plants": [
		{
			"name": "Cactus Mare",
			"id": "1",
			"waterEvery": "1",
			"lastWatered": "2020-04-07",
			"desc": "De la Arta`n`Dar",
			"img": "./img/1.jpeg"
		},
		{
			"name": "Kalanchoe",
			"id": "2",
			"waterEvery": "4",
			"lastWatered": "2020-04-07",
			"desc": "Din Mega Image Obor",
			"img": "./img/2.jpeg"
		},
		{
			"name": "Cactus Mic",
			"id": "3",
			"waterEvery": "2",
			"lastWatered": "2020-04-06",
			"desc": "Din Alexandria, Teleorman",
			"img": "./img/3.jpeg"
		}
	]
}